schema.json
stellapy/__init__.py
stellapy/configuration.py
stellapy/executor.py
stellapy/logger.py
stellapy/reloader.py
stellapy/stella.py
stellapy/walker.py
stellapy-0.4.0.dist-info/LICENSE.txt
stellapy-0.4.0.dist-info/METADATA
stellapy-0.4.0.dist-info/WHEEL
stellapy-0.4.0.dist-info/entry_points.txt
stellapy-0.4.0.dist-info/RECORD
