Metadata-Version: 2.1
Name: stellapy
Version: 0.4.0
Summary: Streamline your web dev experience with stella - reload for the terminal as well as browser.
Home-page: https://github.com/shravanasati/stellapy
License: MIT
Keywords: web dev,development,website,python,cli,stella,reloader,walker,executor,helium,selenium,automation
Author: Shravan Asati
Author-email: dev.shravan@protonmail.com
Requires-Python: >=3.10,<4.0
Classifier: Development Status :: 4 - Beta
Classifier: Intended Audience :: Developers
Classifier: License :: OSI Approved :: MIT License
Classifier: Operating System :: MacOS :: MacOS X
Classifier: Operating System :: Microsoft :: Windows
Classifier: Operating System :: Unix
Classifier: Programming Language :: Python :: 3
Classifier: Programming Language :: Python :: 3.10
Classifier: Programming Language :: Python :: 3.11
Classifier: Programming Language :: Python :: 3.12
Classifier: Programming Language :: Python :: 3.7
Classifier: Programming Language :: Python :: 3.8
Classifier: Programming Language :: Python :: 3.9
Requires-Dist: click (>=8.1.7,<9.0.0)
Requires-Dist: gitignorefile (>=1.1.2,<2.0.0)
Requires-Dist: jsonschema (>=4.20.0,<5.0.0)
Requires-Dist: rich (>=13.7.0,<14.0.0)
Requires-Dist: ruamel-yaml (>=0.18.5,<0.19.0)
Requires-Dist: selenium (>=4.21.0,<5.0.0)
Requires-Dist: watchdog (>=4.0.0,<5.0.0)
Project-URL: Documentation, https://github.com/shravanasati/stellapy#readme
Project-URL: Repository, https://github.com/shravanasati/stellapy
